LICENSE
MANIFEST.in
README.rst
pyproject.toml
requirements.txt
src/auxjad/__init__.py
src/auxjad/_version.py
src/auxjad.egg-info/PKG-INFO
src/auxjad.egg-info/SOURCES.txt
src/auxjad.egg-info/dependency_links.txt
src/auxjad.egg-info/requires.txt
src/auxjad.egg-info/top_level.txt
src/auxjad/__pycache__/__init__.cpython-312.pyc
src/auxjad/__pycache__/_version.cpython-312.pyc
src/auxjad/core/CartographySelector.py
src/auxjad/core/CrossFader.py
src/auxjad/core/Echoer.py
src/auxjad/core/Fader.py
src/auxjad/core/GeneticAlgorithm.py
src/auxjad/core/Hocketer.py
src/auxjad/core/LeafLooper.py
src/auxjad/core/ListLooper.py
src/auxjad/core/Phaser.py
src/auxjad/core/PitchRandomiser.py
src/auxjad/core/Repeater.py
src/auxjad/core/Shuffler.py
src/auxjad/core/TenneySelector.py
src/auxjad/core/WindowLooper.py
src/auxjad/core/_LooperParent.py
src/auxjad/core/__init__.py
src/auxjad/core/__pycache__/CartographySelector.cpython-312.pyc
src/auxjad/core/__pycache__/CrossFader.cpython-312.pyc
src/auxjad/core/__pycache__/Echoer.cpython-312.pyc
src/auxjad/core/__pycache__/Fader.cpython-312.pyc
src/auxjad/core/__pycache__/GeneticAlgorithm.cpython-312.pyc
src/auxjad/core/__pycache__/Hocketer.cpython-312.pyc
src/auxjad/core/__pycache__/LeafLooper.cpython-312.pyc
src/auxjad/core/__pycache__/ListLooper.cpython-312.pyc
src/auxjad/core/__pycache__/Phaser.cpython-312.pyc
src/auxjad/core/__pycache__/PitchRandomiser.cpython-312.pyc
src/auxjad/core/__pycache__/Repeater.cpython-312.pyc
src/auxjad/core/__pycache__/Shuffler.cpython-312.pyc
src/auxjad/core/__pycache__/TenneySelector.cpython-312.pyc
src/auxjad/core/__pycache__/WindowLooper.cpython-312.pyc
src/auxjad/core/__pycache__/_LooperParent.cpython-312.pyc
src/auxjad/core/__pycache__/__init__.cpython-312.pyc
src/auxjad/get/__init__.py
src/auxjad/get/leaves_are_tieable.py
src/auxjad/get/rhythms_are_identical.py
src/auxjad/get/selection_is_full.py
src/auxjad/get/selections_are_identical.py
src/auxjad/get/time_signature_list.py
src/auxjad/get/underfull_duration.py
src/auxjad/get/virtual_fundamental.py
src/auxjad/get/__pycache__/__init__.cpython-312.pyc
src/auxjad/get/__pycache__/leaves_are_tieable.cpython-312.pyc
