Metadata-Version: 2.4
Name: auxjad
Version: 1.0.5
Summary: Auxiliary classes and functions for Abjad.
Author-email: Gilberto Agostinho <gilbertohasnofb@gmail.com>
License: MIT
Project-URL: homepage, https://gilbertohasnofb.github.io/auxjad-docs/
Project-URL: source, https://github.com/gilbertohasnofb/auxjad
Keywords: auxjad,algorithmic composition,generative music,computer music,music composition,music notation,lilypond,abjad
Classifier: Development Status :: 5 - Production/Stable
Classifier: License :: OSI Approved :: MIT License
Classifier: Programming Language :: Python :: 3.9
Classifier: Programming Language :: Python :: 3.10
Classifier: Programming Language :: Python :: 3.11
Classifier: Programming Language :: Python :: 3.12
Classifier: Programming Language :: Python :: 3.13
Classifier: Topic :: Artistic Software
Classifier: Topic :: Utilities
Requires-Python: >=3.9
License-File: LICENSE
Requires-Dist: abjad==3.4
Requires-Dist: flake8==7.2.0
Requires-Dist: isort==6.0.1
Requires-Dist: pydocstyle==6.3.0
Requires-Dist: pytest==8.4.0
Requires-Dist: setuptools==80.9.0
Requires-Dist: sphinx==8.2.3
Dynamic: license-file
